endex_factset_people/__init__.py
endex_factset_people/_base_client.py
endex_factset_people/_client.py
endex_factset_people/_compat.py
endex_factset_people/_constants.py
endex_factset_people/_exceptions.py
endex_factset_people/_files.py
endex_factset_people/_models.py
endex_factset_people/_qs.py
endex_factset_people/_resource.py
endex_factset_people/_response.py
endex_factset_people/_streaming.py
endex_factset_people/_types.py
endex_factset_people/_version.py
endex_factset_people/py.typed
endex_factset_people/_utils/__init__.py
endex_factset_people/_utils/_logs.py
endex_factset_people/_utils/_proxy.py
endex_factset_people/_utils/_reflection.py
endex_factset_people/_utils/_streams.py
endex_factset_people/_utils/_sync.py
endex_factset_people/_utils/_transform.py
endex_factset_people/_utils/_typing.py
endex_factset_people/_utils/_utils.py
endex_factset_people/lib/.keep
endex_factset_people/resources/__init__.py
endex_factset_people/resources/company_stats.py
endex_factset_people/resources/job_histories.py
endex_factset_people/resources/profiles.py
endex_factset_people/resources/companies/__init__.py
endex_factset_people/resources/companies/companies.py
endex_factset_people/resources/companies/compensations.py
endex_factset_people/resources/companies/executives.py
endex_factset_people/resources/companies/positions.py
endex_factset_people/types/__init__.py
endex_factset_people/types/company_stat_create_params.py
endex_factset_people/types/company_stat_retrieve_params.py
endex_factset_people/types/company_stats_response.py
endex_factset_people/types/job_history_create_params.py
endex_factset_people/types/job_history_list_params.py
endex_factset_people/types/people_jobs_response.py
endex_factset_people/types/people_profiles_response.py
endex_factset_people/types/profile_create_params.py
endex_factset_people/types/profile_list_params.py
endex_factset_people/types/companies/__init__.py
endex_factset_people/types/companies/company_compensation_response.py
endex_factset_people-0.1.0a1.dist-info/METADATA
endex_factset_people-0.1.0a1.dist-info/WHEEL
endex_factset_people-0.1.0a1.dist-info/licenses/LICENSE
endex_factset_people-0.1.0a1.dist-info/RECORD
